setup.py
nose_html/__init__.py
nose_html.egg-info/PKG-INFO
nose_html.egg-info/SOURCES.txt
nose_html.egg-info/dependency_links.txt
nose_html.egg-info/entry_points.txt
nose_html.egg-info/requires.txt
nose_html.egg-info/top_level.txt