Metadata-Version: 1.0
Name: nose-html
Version: 1.1
Summary: HTML report generation plugin for nose
Home-page: https://github.com/sio2project/nose-html
Author: Wai Yip Tung, The SIO2 Project Team
Author-email: sio2@sio2project.mimuw.edu.pl
License: BSD
Platform: UNKNOWN
